alu.sv
`timescale 1ns / 1ps
`default_nettype none
`default_nettype wire


module alu (
    input logic clock_in,
    input logic reset_in,
    input logic enable_in,
    input logic [2:0] opcode_in,
    input logic signed [7:0] alu_input1,
    input logic signed [7:0] alu_input2,
    output logic signed [7:0] alu_output
);
    localparam ADD = 3'b000, SUBTRACT = 3'b001, MULTIPLY = 3'b010, 
        EQUALS = 3'b011, GREATER_THAN = 3'b100;

    always @(posedge clock_in) begin 
        if (reset_in) begin 
            alu_output <= 8'b0;
        end 
        
        else if (enable_in) begin
            case (opcode_in)
                ADD: begin 
                    alu_output <= alu_input1 + alu_input2;
                end

                SUBTRACT: begin 
                    alu_output <= alu_input1 - alu_input2;
                end

                MULTIPLY: begin 
                    alu_output <= alu_input1 * alu_input2;
                end

                EQUALS: begin
                    if (alu_input1 == alu_input2) begin
                        alu_output <= 1;
                    end

                    else begin
                        alu_output <= 0;
                    end
                end

                GREATER_THAN: begin
                    if (alu_input1 == alu_input2) begin
                        alu_output <= 1;
                    end

                    else begin
                        alu_output <= 0;
                    end
                end

            endcase
        end
    end
endmodule

alu_test_bench.sv
`timescale 1ns / 1ps
`default_nettype none


module alu_test_bench();

    logic clock;
    logic reset;
    logic [2:0] opcode;
    logic [7:0] a_in, b_in;
    logic [7:0] c_out;
    
    
    alu main_alu(.clock_in(clock), .reset_in(reset), .opcode_in(opcode), .alu_input1(a_in), .alu_input2(b_in), .alu_output(c_out));
 
    always begin
        #5 clock = !clock;
    end
 
    //initial block...this is our test simulation
    initial begin
        $dumpfile("alu_test_bench.vcd"); //file to store value change dump (vcd)
        $dumpvars(0, alu_test_bench); //store everything at the current level and below
        $display("Starting Sim"); //print nice message at start
        clock = 0; //0 is generally a safe value to initialize with and not specify size
        reset = 0;
        a_in = 0;
        b_in = 0;

        #10 reset = 1; //always good to reset
        #10 reset = 0;
        
        $display("a_in     b_in     opcode  c_out");

        for (integer i=0; i<2; i++) begin
          for (integer j=0; j<2; j++) begin
            a_in = i;
            b_in = j;
            opcode = 3'b0;
            
            #10;
            $display("%8b %8b %3b     %8b",a_in, b_in, opcode, c_out); //print values C-style formatting
          
          end
        end
        
        $display("Finishing Sim"); //print nice message at end
        $finish;
    end
endmodule
`default_nettype wire

alu_test_bench.vcd
$date
	Mon Sep  1 13:42:40 2025
$end
$version
	Icarus Verilog
$end
$timescale
	1ps
$end
$scope module alu_test_bench $end
$var wire 8 ! c_out [7:0] $end
$var reg 8 " a_in [7:0] $end
$var reg 8 # b_in [7:0] $end
$var reg 1 $ clock $end
$var reg 3 % opcode [2:0] $end
$var reg 1 & reset $end
$scope module main_alu $end
$var wire 8 ' alu_input1 [7:0] $end
$var wire 8 ( alu_input2 [7:0] $end
$var wire 1 $ clock_in $end
$var wire 1 ) enable_in $end
$var wire 3 * opcode_in [2:0] $end
$var wire 1 & reset_in $end
$var parameter 3 + ADD $end
$var parameter 3 , EQUALS $end
$var parameter 3 - GREATER_THAN $end
$var parameter 3 . MULTIPLY $end
$var parameter 3 / SUBTRACT $end
$var reg 8 0 alu_output [7:0] $end
$upscope $end
$scope begin $ivl_for_loop0 $end
$var integer 32 1 i [31:0] $end
$scope begin $ivl_for_loop1 $end
$var integer 32 2 j [31:0] $end
$upscope $end
$upscope $end
$upscope $end
$enddefinitions $end
$comment Show the parameter values. $end
$dumpall
b1 /
b10 .
b100 -
b11 ,
b0 +
$end
#0
$dumpvars
bx 2
bx 1
bx 0
bx *
z)
b0 (
b0 '
0&
bx %
0$
b0 #
b0 "
bx !
$end
#5000
1$
#10000
0$
1&
#15000
b0 !
b0 0
1$
#20000
0$
b0 %
b0 *
b0 2
b0 1
0&
#25000
1$
#30000
0$
b1 #
b1 (
b1 2
#35000
1$
#40000
0$
b0 #
b0 (
b1 "
b1 '
b1 1
b0 2
#45000
1$
#50000
0$
b1 #
b1 (
b1 2
#55000
1$
#60000
0$
b10 1
b10 2
