alu.sv
`timescale 1ns / 1ps
`default_nettype none
`default_nettype wire


module alu (
    input logic clock_in,
    input logic reset_in,
    input logic enable_in,
    input logic [2:0] opcode_in,
    input logic signed [7:0] alu_input1,
    input logic signed [7:0] alu_input2,
    output logic signed [7:0] alu_output
);
    localparam ADD = 3'b000, SUBTRACT = 3'b001, MULTIPLY = 3'b010, 
        EQUALS = 3'b011, GREATER_THAN = 3'b100;

    always @(posedge clock_in) begin 
        if (reset_in) begin 
            alu_output <= 8'b0;
        end 
        
        else if (enable_in) begin
            case (opcode_in)
                ADD: begin 
                    alu_output <= alu_input1 + alu_input2;
                end

                SUBTRACT: begin 
                    alu_output <= alu_input1 - alu_input2;
                end

                MULTIPLY: begin 
                    alu_output <= alu_input1 * alu_input2;
                end

                EQUALS: begin
                    if (alu_input1 == alu_input2) begin
                        alu_output <= 1;
                    end

                    else begin
                        alu_output <= 0;
                    end
                end

                GREATER_THAN: begin
                    if (alu_input1 == alu_input2) begin
                        alu_output <= 1;
                    end

                    else begin
                        alu_output <= 0;
                    end
                end

            endcase
        end
    end
endmodule

alu_test_bench.sv
`timescale 1ns / 1ps
`default_nettype none


module alu_test_bench();

    logic clock;
    logic reset;
    logic [2:0] alu_opcode;
    logic [7:0] alu_input1, alu_input2;
    logic [7:0] alu_output;
    
    
    alu main_alu(
        .clock_in(clock), .reset_in(reset), .enable_in(1'b1), 
        .opcode_in(alu_opcode), .alu_input1(alu_input1), .alu_input2(alu_input2), 
        .alu_output(alu_output)
    );

    always begin
        #5 clock = !clock;
    end
 


    initial begin
        $dumpfile("alu_test_bench.vcd"); //file to store value change dump (vcd)
        $dumpvars(0, alu_test_bench); //store everything at the current level and below


        clock = 0;
        reset = 0;
        alu_input1 = 0;
        alu_input2 = 0;

        #10 reset = 1; // reset cycle
        #10 reset = 0;
        
        // header
        $display("  alu_input1    alu_input2   opcode       alu_output");

        // test addition opcode
        for (integer i=10; i<20; i++) begin
          for (integer j=15; j<20; j++) begin
            alu_input1 = i;
            alu_input2 = j;
            alu_opcode = 3'b0;
            
            #30;
            $display("%d           %d            %3b        %d",alu_input1, alu_input2, alu_opcode, alu_output); //print values C-style formatting

            if (alu_output !== alu_input1 + alu_input2) begin
                $error("Mismatch: Expected %h, Got %h at time %0t", alu_input1 + alu_input2, alu_output, $time);
            end

          end
        end
        





        $display("Finishing Sim"); //print nice message at end
        $finish;
    end
endmodule
`default_nettype wire

alu_test_bench.vcd
$date
	Mon Sep  1 14:14:14 2025
$end
$version
	Icarus Verilog
$end
$timescale
	1ps
$end
$scope module alu_test_bench $end
$var wire 8 ! alu_output [7:0] $end
$var reg 8 " alu_input1 [7:0] $end
$var reg 8 # alu_input2 [7:0] $end
$var reg 3 $ alu_opcode [2:0] $end
$var reg 1 % clock $end
$var reg 1 & reset $end
$scope module main_alu $end
$var wire 8 ' alu_input1 [7:0] $end
$var wire 8 ( alu_input2 [7:0] $end
$var wire 1 % clock_in $end
$var wire 1 ) enable_in $end
$var wire 3 * opcode_in [2:0] $end
$var wire 1 & reset_in $end
$var parameter 3 + ADD $end
$var parameter 3 , EQUALS $end
$var parameter 3 - GREATER_THAN $end
$var parameter 3 . MULTIPLY $end
$var parameter 3 / SUBTRACT $end
$var reg 8 0 alu_output [7:0] $end
$upscope $end
$scope begin $ivl_for_loop0 $end
$var integer 32 1 i [31:0] $end
$scope begin $ivl_for_loop1 $end
$var integer 32 2 j [31:0] $end
$upscope $end
$upscope $end
$upscope $end
$enddefinitions $end
$comment Show the parameter values. $end
$dumpall
b1 /
b10 .
b100 -
b11 ,
b0 +
$end
#0
$dumpvars
bx 2
bx 1
bx 0
bx *
1)
b0 (
b0 '
0&
0%
bx $
b0 #
b0 "
bx !
$end
#5000
1%
#10000
0%
1&
#15000
b0 !
b0 0
1%
#20000
0%
b0 $
b0 *
b1111 #
b1111 (
b1010 "
b1010 '
b1111 2
b1010 1
0&
#25000
b11001 !
b11001 0
1%
#30000
0%
#35000
1%
#40000
0%
#45000
1%
#50000
0%
b10000 #
b10000 (
b10000 2
#55000
b11010 !
b11010 0
1%
#60000
0%
#65000
1%
#70000
0%
#75000
1%
#80000
0%
b10001 #
b10001 (
b10001 2
#85000
b11011 !
b11011 0
1%
#90000
0%
#95000
1%
#100000
0%
#105000
1%
#110000
0%
b10010 #
b10010 (
b10010 2
#115000
b11100 !
b11100 0
1%
#120000
0%
#125000
1%
#130000
0%
#135000
1%
#140000
0%
b10011 #
b10011 (
b10011 2
#145000
b11101 !
b11101 0
1%
#150000
0%
#155000
1%
#160000
0%
#165000
1%
#170000
0%
b1111 #
b1111 (
b1011 "
b1011 '
b1011 1
b1111 2
#175000
b11010 !
b11010 0
1%
#180000
0%
#185000
1%
#190000
0%
#195000
1%
#200000
0%
b10000 #
b10000 (
b10000 2
#205000
b11011 !
b11011 0
1%
#210000
0%
#215000
1%
#220000
0%
#225000
1%
#230000
0%
b10001 #
b10001 (
b10001 2
#235000
b11100 !
b11100 0
1%
#240000
0%
#245000
1%
#250000
0%
#255000
1%
#260000
0%
b10010 #
b10010 (
b10010 2
#265000
b11101 !
b11101 0
1%
#270000
0%
#275000
1%
#280000
0%
#285000
1%
#290000
0%
b10011 #
b10011 (
b10011 2
#295000
b11110 !
b11110 0
1%
#300000
0%
#305000
1%
#310000
0%
#315000
1%
#320000
0%
b1111 #
b1111 (
b1100 "
b1100 '
b1100 1
b1111 2
#325000
b11011 !
b11011 0
1%
#330000
0%
#335000
1%
#340000
0%
#345000
1%
#350000
0%
b10000 #
b10000 (
b10000 2
#355000
b11100 !
b11100 0
1%
#360000
0%
#365000
1%
#370000
0%
#375000
1%
#380000
0%
b10001 #
b10001 (
b10001 2
#385000
b11101 !
b11101 0
1%
#390000
0%
#395000
1%
#400000
0%
#405000
1%
#410000
0%
b10010 #
b10010 (
b10010 2
#415000
b11110 !
b11110 0
1%
#420000
0%
#425000
1%
#430000
0%
#435000
1%
#440000
0%
b10011 #
b10011 (
b10011 2
#445000
b11111 !
b11111 0
1%
#450000
0%
#455000
1%
#460000
0%
#465000
1%
#470000
0%
b1111 #
b1111 (
b1101 "
b1101 '
b1101 1
b1111 2
#475000
b11100 !
b11100 0
1%
#480000
0%
#485000
1%
#490000
0%
#495000
1%
#500000
0%
b10000 #
b10000 (
b10000 2
#505000
b11101 !
b11101 0
1%
#510000
0%
#515000
1%
#520000
0%
#525000
1%
#530000
0%
b10001 #
b10001 (
b10001 2
#535000
b11110 !
b11110 0
1%
#540000
0%
#545000
1%
#550000
0%
#555000
1%
#560000
0%
b10010 #
b10010 (
b10010 2
#565000
b11111 !
b11111 0
1%
#570000
0%
#575000
1%
#580000
0%
#585000
1%
#590000
0%
b10011 #
b10011 (
b10011 2
#595000
b100000 !
b100000 0
1%
#600000
0%
#605000
1%
#610000
0%
#615000
1%
#620000
0%
b1111 #
b1111 (
b1110 "
b1110 '
b1110 1
b1111 2
#625000
b11101 !
b11101 0
1%
#630000
0%
#635000
1%
#640000
0%
#645000
1%
#650000
0%
b10000 #
b10000 (
b10000 2
#655000
b11110 !
b11110 0
1%
#660000
0%
#665000
1%
#670000
0%
#675000
1%
#680000
0%
b10001 #
b10001 (
b10001 2
#685000
b11111 !
b11111 0
1%
#690000
0%
#695000
1%
#700000
0%
#705000
1%
#710000
0%
b10010 #
b10010 (
b10010 2
#715000
b100000 !
b100000 0
1%
#720000
0%
#725000
1%
#730000
0%
#735000
1%
#740000
0%
b10011 #
b10011 (
b10011 2
#745000
b100001 !
b100001 0
1%
#750000
0%
#755000
1%
#760000
0%
#765000
1%
#770000
0%
b1111 #
b1111 (
b1111 "
b1111 '
b1111 1
b1111 2
#775000
b11110 !
b11110 0
1%
#780000
0%
#785000
1%
#790000
0%
#795000
1%
#800000
0%
b10000 #
b10000 (
b10000 2
#805000
b11111 !
b11111 0
1%
#810000
0%
#815000
1%
#820000
0%
#825000
1%
#830000
0%
b10001 #
b10001 (
b10001 2
#835000
b100000 !
b100000 0
1%
#840000
0%
#845000
1%
#850000
0%
#855000
1%
#860000
0%
b10010 #
b10010 (
b10010 2
#865000
b100001 !
b100001 0
1%
#870000
0%
#875000
1%
#880000
0%
#885000
1%
#890000
0%
b10011 #
b10011 (
b10011 2
#895000
b100010 !
b100010 0
1%
#900000
0%
#905000
1%
#910000
0%
#915000
1%
#920000
0%
b1111 #
b1111 (
b10000 "
b10000 '
b10000 1
b1111 2
#925000
b11111 !
b11111 0
1%
#930000
0%
#935000
1%
#940000
0%
#945000
1%
#950000
0%
b10000 #
b10000 (
b10000 2
#955000
b100000 !
b100000 0
1%
#960000
0%
#965000
1%
#970000
0%
#975000
1%
#980000
0%
b10001 #
b10001 (
b10001 2
#985000
b100001 !
b100001 0
1%
#990000
0%
#995000
1%
#1000000
0%
#1005000
1%
#1010000
0%
b10010 #
b10010 (
b10010 2
#1015000
b100010 !
b100010 0
1%
#1020000
0%
#1025000
1%
#1030000
0%
#1035000
1%
#1040000
0%
b10011 #
b10011 (
b10011 2
#1045000
b100011 !
b100011 0
1%
#1050000
0%
#1055000
1%
#1060000
0%
#1065000
1%
#1070000
0%
b1111 #
b1111 (
b10001 "
b10001 '
b10001 1
b1111 2
#1075000
b100000 !
b100000 0
1%
#1080000
0%
#1085000
1%
#1090000
0%
#1095000
1%
#1100000
0%
b10000 #
b10000 (
b10000 2
#1105000
b100001 !
b100001 0
1%
#1110000
0%
#1115000
1%
#1120000
0%
#1125000
1%
#1130000
0%
b10001 #
b10001 (
b10001 2
#1135000
b100010 !
b100010 0
1%
#1140000
0%
#1145000
1%
#1150000
0%
#1155000
1%
#1160000
0%
b10010 #
b10010 (
b10010 2
#1165000
b100011 !
b100011 0
1%
#1170000
0%
#1175000
1%
#1180000
0%
#1185000
1%
#1190000
0%
b10011 #
b10011 (
b10011 2
#1195000
b100100 !
b100100 0
1%
#1200000
0%
#1205000
1%
#1210000
0%
#1215000
1%
#1220000
0%
b1111 #
b1111 (
b10010 "
b10010 '
b10010 1
b1111 2
#1225000
b100001 !
b100001 0
1%
#1230000
0%
#1235000
1%
#1240000
0%
#1245000
1%
#1250000
0%
b10000 #
b10000 (
b10000 2
#1255000
b100010 !
b100010 0
1%
#1260000
0%
#1265000
1%
#1270000
0%
#1275000
1%
#1280000
0%
b10001 #
b10001 (
b10001 2
#1285000
b100011 !
b100011 0
1%
#1290000
0%
#1295000
1%
#1300000
0%
#1305000
1%
#1310000
0%
b10010 #
b10010 (
b10010 2
#1315000
b100100 !
b100100 0
1%
#1320000
0%
#1325000
1%
#1330000
0%
#1335000
1%
#1340000
0%
b10011 #
b10011 (
b10011 2
#1345000
b100101 !
b100101 0
1%
#1350000
0%
#1355000
1%
#1360000
0%
#1365000
1%
#1370000
0%
b1111 #
b1111 (
b10011 "
b10011 '
b10011 1
b1111 2
#1375000
b100010 !
b100010 0
1%
#1380000
0%
#1385000
1%
#1390000
0%
#1395000
1%
#1400000
0%
b10000 #
b10000 (
b10000 2
#1405000
b100011 !
b100011 0
1%
#1410000
0%
#1415000
1%
#1420000
0%
#1425000
1%
#1430000
0%
b10001 #
b10001 (
b10001 2
#1435000
b100100 !
b100100 0
1%
#1440000
0%
#1445000
1%
#1450000
0%
#1455000
1%
#1460000
0%
b10010 #
b10010 (
b10010 2
#1465000
b100101 !
b100101 0
1%
#1470000
0%
#1475000
1%
#1480000
0%
#1485000
1%
#1490000
0%
b10011 #
b10011 (
b10011 2
#1495000
b100110 !
b100110 0
1%
#1500000
0%
#1505000
1%
#1510000
0%
#1515000
1%
#1520000
0%
b10100 1
b10100 2
